appcommands/__init__.py
appcommands/__main__.py
appcommands/appbot.py
appcommands/client.py
appcommands/cog.py
appcommands/core.py
appcommands/enums.py
appcommands/utils.py
dpy_appcommands-2.0.4.5.dist-info/LICENSE
dpy_appcommands-2.0.4.5.dist-info/METADATA
dpy_appcommands-2.0.4.5.dist-info/WHEEL
dpy_appcommands-2.0.4.5.dist-info/entry_points.txt
dpy_appcommands-2.0.4.5.dist-info/top_level.txt
dpy_appcommands-2.0.4.5.dist-info/RECORD
