Metadata-Version: 2.1
Name: dpy-appcommands
Version: 2.0.4.5
Summary: A module for creating and using application commands on discord.
Home-page: UNKNOWN
Author: Rishiraj0100
License: MIT
Project-URL: Documentation, https://dpy-appcommands.rtfd.io/
Project-URL: Issue tracker, https://github.com/Rishiraj0100/dpy-appcommands/issues
Platform: UNKNOWN
Classifier: Programming Language :: Python
Classifier: Programming Language :: Python :: 3.8
Classifier: Programming Language :: Python :: 3.9
Classifier: Programming Language :: Python :: 3.10
Classifier: License :: OSI Approved :: MIT License
Classifier: Operating System :: OS Independent
Requires-Python: >=3.8
License-File: LICENSE
